mypycolorizer/colorizer.py
mypycolorizer-0.1.dist-info/LICENSE
mypycolorizer-0.1.dist-info/METADATA
mypycolorizer-0.1.dist-info/WHEEL
mypycolorizer-0.1.dist-info/top_level.txt
mypycolorizer-0.1.dist-info/RECORD
