Metadata-Version: 2.1
Name: mypycolorizer
Version: 0.1
Summary: A simple way to add color to your Python CLI apps
Home-page: https://github.com/davebowlin/pycolorizer
Author: Decryptionator
Author-email: davebowlin@duck.com
License: MIT
Classifier: Development Status :: 3 - Alpha
Classifier: Intended Audience :: Developers
Classifier: License :: OSI Approved :: MIT License
Classifier: Programming Language :: Python :: 3
Classifier: Programming Language :: Python :: 3.6
Classifier: Programming Language :: Python :: 3.7
Classifier: Programming Language :: Python :: 3.8
Classifier: Programming Language :: Python :: 3.9
Classifier: Programming Language :: Python :: 3.10
Classifier: Programming Language :: Python :: 3.11
License-File: LICENSE
